admin_reorder/__init__.py
admin_reorder/__pycache__/__init__.cpython-312.pyc
django_modeladmin_reorder_reborn_again-0.1.1.dist-info/licenses/AUTHORS.md
django_modeladmin_reorder_reborn_again-0.1.1.dist-info/licenses/LICENSE
django_modeladmin_reorder_reborn_again-0.1.1.dist-info/METADATA
django_modeladmin_reorder_reborn_again-0.1.1.dist-info/WHEEL
django_modeladmin_reorder_reborn_again-0.1.1.dist-info/top_level.txt
django_modeladmin_reorder_reborn_again-0.1.1.dist-info/RECORD
