Metadata-Version: 2.4
Name: django-modeladmin-reorder-reborn-again
Version: 0.1.1
Summary: Custom ordering for the apps and models in the admin app.
Home-page: https://github.com/amphr/django-modeladmin-reorder-reborn-again
Author: amphr
Author-email: 
License: BSD-3-Clause
Project-URL: Homepage, https://github.com/amphr/django-modeladmin-reorder-reborn-again
Classifier: Environment :: Web Environment
Classifier: Framework :: Django
Classifier: Framework :: Django :: 4.1
Classifier: Intended Audience :: Developers
Classifier: License :: OSI Approved :: BSD License
Classifier: Operating System :: OS Independent
Classifier: Programming Language :: Python
Classifier: Topic :: Internet :: WWW/HTTP
Classifier: Topic :: Internet :: WWW/HTTP :: Dynamic Content
Requires-Python: >=3.5
License-File: LICENSE
License-File: AUTHORS.md
Requires-Dist: Django>=4.1
Dynamic: home-page
Dynamic: license-file
Dynamic: requires-python
